setup.py
JIM_client.egg-info/PKG-INFO
JIM_client.egg-info/SOURCES.txt
JIM_client.egg-info/dependency_links.txt
JIM_client.egg-info/requires.txt
JIM_client.egg-info/top_level.txt
client/__init__.py
client/client.py
client/client/__init__.py
client/client/client_db.py
client/client/client_gui.py
client/client/client_user.py
client/client/launcher.py
client/common/__init__.py
client/common/setting.py
client/common/utils.py
client/decorators/__init__.py
client/decorators/decorators.py
client/descriptors/__init__.py
client/descriptors/descriptors.py
client/log/__init__.py
client/log/client/__init__.py
client/log/client/client_log.py
client/log/server/__init__.py
client/log/server/server_log.py
client/log/utils/__init__.py
client/log/utils/utils_log.py
client/metaclasses/__init__.py
client/metaclasses/metaclasses.py
client/tests/__init__.py
client/tests/protocols_test.py
client/tests/server_test.py