Metadata-Version: 1.0
Name: JIM-client
Version: 0.0.1
Summary: messegers client
Home-page: UNKNOWN
Author: Firdos Aliev
Author-email: firdos1234567891@gmail.com
License: UNKNOWN
Platform: UNKNOWN
